cbquant/cbquant.py
cbquant/cli.py
cbquant-0.1.dist-info/LICENSE
cbquant-0.1.dist-info/METADATA
cbquant-0.1.dist-info/WHEEL
cbquant-0.1.dist-info/entry_points.txt
cbquant-0.1.dist-info/top_level.txt
cbquant-0.1.dist-info/zip-safe
cbquant-0.1.dist-info/RECORD
