Metadata-Version: 2.1
Name: cbquant
Version: 0.1
Summary: Lossy Comic Book Archive Compressor
Home-page: https://pypi.python.org/pypi/cbquant
Author: Reece Walsh
Author-email: reece@brikwerk.com
License: GPLV3
Project-URL: Code, https://github.com/Brikwerk/cbquant
Project-URL: Issue tracker, https://github.com/Brikwerk/cbquant/issues
Platform: any
Classifier: Development Status :: 3 - Alpha
Classifier: Intended Audience :: Developers
Classifier: License :: OSI Approved :: MIT License
Classifier: Operating System :: OS Independent
Classifier: Programming Language :: Python
Classifier: Programming Language :: Python :: 3.8
Classifier: Programming Language :: Python :: 3.9
Classifier: Programming Language :: Python :: 3.10
Classifier: Topic :: Software Development :: Libraries :: Python Modules
Requires-Python: >=3.8
License-File: LICENSE
Requires-Dist: libimagequant
Requires-Dist: libimagequant-integrations
Requires-Dist: Pillow
Requires-Dist: tqdm
